{
  "created_at": "Tue Sep 28 2021 08:00:23 GMT+0200 (Central European Summer Time)",
  "id": 2,
  "id_str": "3",
  "text": "thyme naga jolokia salt cod fish thyme california reaper tofu chicken liver california reaper seitan",
  "source": "sucrose",
  "truncated": false,
  "in_reply_to_status_id": null,
  "in_reply_to_status_id_str": null,
  "in_reply_to_user_id": null,
  "in_reply_to_user_id_str": null,
  "in_reply_to_screen_name": null,
  "user": {
    "id": 13,
    "id_str": "14",
    "name": "wonder_brand",
    "screen_name": "wonder_brand",
    "location": null,
    "url": null,
    "description": null,
    "translator_type": "chicken",
    "protected": false,
    "verified": false,
    "followers_count": 6474,
    "friends_count": 4317,
    "listed_count": 5452,
    "favourites_count": 5638,
    "statuses_count": 4524,
    "created_at": "Tue Sep 28 2021 08:00:23 GMT+0200 (Central European Summer Time)",
    "utc_offset": null,
    "time_zone": null,
    "geo_enabled": false,
    "lang": null,
    "contributors_enabled": false,
    "is_translator": false,
    "profile_background_color": "oregano",
    "profile_background_image_url": "beef",
    "profile_background_image_url_https": "seitan",
    "profile_background_tile": false,
    "profile_link_color": "sugar",
    "profile_sidebar_border_color": "naga jolokia",
    "profile_sidebar_fill_color": "coffee",
    "profile_text_color": "thyme salt oregano seitan coffee mint oregano tuna chicken liver edamame",
    "profile_use_background_image": true,
    "profile_image_url": "cod fish",
    "profile_image_url_https": "california reaper",
    "default_profile": true,
    "default_profile_image": false,
    "following": null,
    "follow_request_sent": null,
    "notifications": null
  },
  "geo": null,
  "coordinates": null,
  "place": null,
  "contributors": null,
  "retweeted_status": {
    "created_at": "Tue Sep 28 2021 08:00:23 GMT+0200 (Central European Summer Time)",
    "id": 57,
    "id_str": "58",
    "text": "seitan california reaper sucrose naga jolokia coffee chicken liver seitan pepper pepper coffee",
    "source": "naga jolokia",
    "truncated": true,
    "in_reply_to_status_id": null,
    "in_reply_to_status_id_str": null,
    "in_reply_to_user_id": null,
    "in_reply_to_user_id_str": null,
    "in_reply_to_screen_name": null,
    "user": {
      "id": 68,
      "id_str": "69",
      "name": "lola_montes",
      "screen_name": "super_man",
      "location": "parsley",
      "url": "seitan",
      "description": "chicken",
      "translator_type": "thyme",
      "protected": false,
      "verified": false,
      "followers_count": 8645,
      "friends_count": 5557,
      "listed_count": 5057,
      "favourites_count": 5267,
      "statuses_count": 8891,
      "created_at": "Tue Sep 28 2021 08:00:23 GMT+0200 (Central European Summer Time)",
      "utc_offset": null,
      "time_zone": null,
      "geo_enabled": true,
      "lang": null,
      "contributors_enabled": false,
      "is_translator": false,
      "profile_background_color": "pepper",
      "profile_background_image_url": "tofu",
      "profile_background_image_url_https": "cinnamon",
      "profile_background_tile": false,
      "profile_link_color": "naga jolokia",
      "profile_sidebar_border_color": "edamame",
      "profile_sidebar_fill_color": "parsley",
      "profile_text_color": "oregano  pepper  chicken liver salt mint sucrose edamame naga jolokia",
      "profile_use_background_image": true,
      "profile_image_url": "california reaper",
      "profile_image_url_https": "oregano",
      "profile_banner_url": "naga jolokia",
      "default_profile": true,
      "default_profile_image": false,
      "following": null,
      "follow_request_sent": null,
      "notifications": null
    },
    "geo": null,
    "coordinates": null,
    "place": null,
    "contributors": null,
    "is_quote_status": false,
    "extended_tweet": {
      "full_text": "coffee beef oregano parsley pepper pepper tofu sugar oregano thyme",
      "display_text_range": [
        3588,
        5657
      ],
      "entities": {
        "hashtags": [
          {
            "text": "tofu sugar oregano naga jolokia cod fish chicken chicken pepper sugar ",
            "indices": [
              4120,
              664
            ]
          }
        ],
        "urls": [
          {
            "url": "tofu",
            "expanded_url": "tofu",
            "display_url": "california reaper",
            "indices": [
              3732,
              1326
            ]
          }
        ],
        "user_mentions": [
          {
            "screen_name": "los_montaditos",
            "name": "woman_super",
            "id": 127,
            "id_str": "128",
            "indices": [
              4107,
              147
            ]
          },
          {
            "screen_name": "los_montaditos",
            "name": "los_montaditos",
            "id": 132,
            "id_str": "133",
            "indices": [
              595,
              7741
            ]
          }
        ],
        "symbols": []
      }
    },
    "quote_count": 5607,
    "reply_count": 1725,
    "retweet_count": 2937,
    "favorite_count": 6972,
    "entities": {
      "hashtags": [],
      "urls": [
        {
          "url": "salt",
          "expanded_url": "sugar",
          "display_url": "pepper",
          "indices": [
            4000,
            2149
          ]
        }
      ],
      "user_mentions": [
        {
          "screen_name": "lola_montes",
          "name": "",
          "id": 150,
          "id_str": "151",
          "indices": [
            6995,
            8573
          ]
        },
        {
          "screen_name": "los_montaditos",
          "name": "fantastic_javi",
          "id": 155,
          "id_str": "156",
          "indices": [
            5339,
            8536
          ]
        }
      ],
      "symbols": []
    },
    "favorited": false,
    "retweeted": false,
    "possibly_sensitive": false,
    "filter_level": "tuna",
    "lang": "pepper"
  },
  "is_quote_status": false,
  "quote_count": 5330,
  "reply_count": 3546,
  "retweet_count": 556,
  "favorite_count": 2396,
  "entities": {
    "hashtags": [],
    "urls": [],
    "user_mentions": [
      {
        "screen_name": "woman_super",
        "name": "sunflower_oil",
        "id": 175,
        "id_str": "176",
        "indices": [
          1596,
          1112
        ]
      },
      {
        "screen_name": "super_man",
        "name": "super_man",
        "id": 180,
        "id_str": "181",
        "indices": [
          3847,
          4159
        ]
      },
      {
        "screen_name": "wonder_brand",
        "name": "uber_joao",
        "id": 185,
        "id_str": "186",
        "indices": [
          2969,
          4944
        ]
      }
    ],
    "symbols": []
  },
  "favorited": false,
  "retweeted": false,
  "filter_level": "edamame",
  "lang": "oregano",
  "timestamp_ms": "1234567890"
}